rival_ai/__init__.py
rival_ai/config.py
rival_ai/exceptions.py
rival_ai/ai_attack_detector/__init__.py
rival_ai/ai_attack_detector/config.py
rival_ai/ai_attack_detector/detector.py
rival_ai/ai_attack_detector/inference_example.py
rival_ai/ai_attack_detector/train_and_deploy.py
rival_ai/ai_attack_detector/data/__init__.py
rival_ai/ai_attack_detector/data/dataset.py
rival_ai/ai_attack_detector/models/__init__.py
rival_ai/ai_attack_detector/models/classifier.py
rival_ai/ai_attack_detector/models/trainer.py
rival_ai/ai_attack_detector/utils/__init__.py
rival_ai/ai_attack_detector/utils/preprocessing.py
rival_ai/core/__init__.py
rival_ai/core/agent_definition.py
rival_ai/core/benchmarking.py
rival_ai/core/benchmarking_result.py
rival_ai/core/evaluation.py
rival_ai/core/testcase.py
rival_ai/detectors/__init__.py
rival_ai/detectors/bhairava/__init__.py
rival_ai/detectors/bhairava/detector.py
rival_ai/detectors/bhairava/train_and_deploy.py
rival_ai/detectors/bhairava/data/__init__.py
rival_ai/detectors/bhairava/data/dataset.py
rival_ai/detectors/bhairava/models/__init__.py
rival_ai/detectors/bhairava/models/classifier.py
rival_ai/detectors/bhairava/models/trainer.py
rival_ai/detectors/bhairava/utils/__init__.py
rival_ai/detectors/bhairava/utils/preprocessing.py
rival_ai/detectors/narasimha/__init__.py
rival_ai/detectors/narasimha/detector.py
rival_ai/evaluators/__init__.py
rival_ai/evaluators/local_evaluator.py
rival_ai/evaluators/prompts.py
rival_ai/generators/__init__.py
rival_ai/generators/testcase_generator.py
rival_ai/generators/attack_criteria/__init__.py
rival_ai/generators/attack_criteria/models.py
rival_ai/generators/attack_criteria/registry.py
rival_ai/generators/attack_criteria/attacks/__init__.py
rival_ai/generators/attack_criteria/attacks/advanced_criteria.py
rival_ai/generators/attack_criteria/attacks/harmful_content_generation.py
rival_ai/generators/attack_criteria/attacks/privacy_and_data_security.py
rival_ai-0.1.7.dist-info/METADATA
rival_ai-0.1.7.dist-info/WHEEL
rival_ai-0.1.7.dist-info/top_level.txt
rival_ai-0.1.7.dist-info/RECORD
