Metadata-Version: 2.4
Name: rival-ai
Version: 0.1.7
Summary: A library for testing and protecting AI agent safety
Author: Sarthak Rastogi
Classifier: Intended Audience :: Developers
Classifier: Programming Language :: Python :: 3
Classifier: Programming Language :: Python :: 3.8
Classifier: Programming Language :: Python :: 3.9
Classifier: Programming Language :: Python :: 3.10
Classifier: Programming Language :: Python :: 3.11
Requires-Python: >=3.8
Requires-Dist: pydantic>=2.0.0
Requires-Dist: litellm>=1.66.1
Requires-Dist: torch>=2.0.0
Requires-Dist: transformers>=4.30.0
Requires-Dist: sentence-transformers>=2.2.0
Requires-Dist: scikit-learn>=1.3.0
Requires-Dist: pandas>=2.0.0
Requires-Dist: numpy>=1.24.0
Requires-Dist: huggingface_hub>=0.16.0
Requires-Dist: datasets>=2.14.0
Requires-Dist: accelerate>=0.20.0
Provides-Extra: dev
Requires-Dist: pytest>=7.0.0; extra == "dev"
Requires-Dist: black>=22.0.0; extra == "dev"
Dynamic: author
Dynamic: classifier
Dynamic: description
Dynamic: description-content-type
Dynamic: provides-extra
Dynamic: requires-dist
Dynamic: requires-python
Dynamic: summary
